tifftag/__main__.py
tifftag/drop_v3.py
tifftag/dropTo.ui
tifftag/ioTIFF_v2.py
tifftag-0.1.3.dist-info/entry_points.txt
tifftag-0.1.3.dist-info/LICENSE
tifftag-0.1.3.dist-info/METADATA
tifftag-0.1.3.dist-info/WHEEL
tifftag-0.1.3.dist-info/RECORD
